cliqestimrie/__init__.py
cliqestimrie/clinetwork.cpython-311-darwin.so
cliqestimrie-0.1.1.dist-info/LICENSE.txt
cliqestimrie-0.1.1.dist-info/METADATA
cliqestimrie-0.1.1.dist-info/WHEEL
cliqestimrie-0.1.1.dist-info/top_level.txt
cliqestimrie-0.1.1.dist-info/RECORD
